MANIFEST.in
setup.py
pymal/__init__.py
pymal/account.py
pymal/anime.py
pymal/consts.py
pymal/decorators.py
pymal/global_functions.py
pymal/manga.py
pymal/seasons.py
pymal.egg-info/PKG-INFO
pymal.egg-info/SOURCES.txt
pymal.egg-info/dependency_links.txt
pymal.egg-info/requires.txt
pymal.egg-info/top_level.txt
pymal/account_objects/__init__.py
pymal/account_objects/account_animes.py
pymal/account_objects/account_friends.py
pymal/account_objects/account_mangas.py
pymal/account_objects/my_anime.py
pymal/account_objects/my_manga.py
pymal/exceptions/__init__.py
pymal/exceptions/failed_to_parse_error.py
pymal/exceptions/my_anime_list_api_error.py
pymal/inner_objects/__init__.py
pymal/inner_objects/recommendation.py
pymal/inner_objects/review.py
pymal/inner_objects/season.py
pymal/searches/README.md
pymal/searches/__init__.py
pymal/searches/search_accounts_provider.py
pymal/searches/search_animes_provider.py
pymal/searches/search_mangas_provider.py
pymal/searches/search_provider.py
pymal/types/README.md
pymal/types/ReloadedSet.py
pymal/types/__init__.py